README.md
setup.py
pulumi_statuspage/__init__.py
pulumi_statuspage/_utilities.py
pulumi_statuspage/component.py
pulumi_statuspage/component_group.py
pulumi_statuspage/metric.py
pulumi_statuspage/metrics_provider.py
pulumi_statuspage/provider.py
pulumi_statuspage/pulumi-plugin.json
pulumi_statuspage/py.typed
pulumi_statuspage.egg-info/PKG-INFO
pulumi_statuspage.egg-info/SOURCES.txt
pulumi_statuspage.egg-info/dependency_links.txt
pulumi_statuspage.egg-info/not-zip-safe
pulumi_statuspage.egg-info/requires.txt
pulumi_statuspage.egg-info/top_level.txt
pulumi_statuspage/config/__init__.py
pulumi_statuspage/config/vars.py