Metadata-Version: 2.1
Name: pulumi-statuspage
Version: 0.1.10
Summary: A Pulumi package for creating and managing statuspage cloud resources.
Home-page: https://github.com/mortaelth/pulumi-statuspage-provider
License: Apache-2.0
Project-URL: Repository, https://github.com/mortaelth/pulumi-statuspage-provider
Keywords: pulumi statuspage category/cloud
Platform: UNKNOWN
Requires-Python: >=3.7
